fast_gsdmm.cpython-38-darwin.so
fast_gsdmm-0.0.1.dist-info/LICENSE
fast_gsdmm-0.0.1.dist-info/METADATA
fast_gsdmm-0.0.1.dist-info/WHEEL
fast_gsdmm-0.0.1.dist-info/top_level.txt
fast_gsdmm-0.0.1.dist-info/RECORD
